atsphinx/buildtime.py
atsphinx_buildtime-0.0.1.dist-info/METADATA
atsphinx_buildtime-0.0.1.dist-info/WHEEL
atsphinx_buildtime-0.0.1.dist-info/top_level.txt
atsphinx_buildtime-0.0.1.dist-info/RECORD
