Metadata-Version: 2.1
Name: atsphinx-buildtime
Version: 0.0.1
Summary: Simple build-time logger for Sphinx.
Requires-Python: >=3.7
Requires-Dist: Sphinx
